cpe324/Homework1/Sim1/mealy.v
module mealy(A, B, OUT, STATE);

    input A, B;                                                 // inputs to add             
    output reg OUT;                                             // sum of the inputs
    output reg CARRY = 0;                                       // carry bit
    output reg STATE = 0;                                       // current state

    always @(A or B)
    begin
        if (A == 1 & B == 1)                                    // if A and B are one 
        begin
            OUT = CARRY + A + B;                                // sum everything up
            CARRY = 1;                                          // carry bit is now 1
            STATE = 1;                                          // state bit is now one
        end

        else if(A == 0 & B == 0)                                // if A and B are both 0
        begin
            OUT = CARRY + A + B;                                // handle the carry
            CARRY = 0;                                          // set carry bit to 0
            STATE = 0;                                          // go to state 0
        end

        else
        begin
            OUT = A + B + CARRY;                                // sum everything up
        end
    end

endmodule

cpe324/Homework1/Sim1/mealy_tb.v
`timescale 1s/100ms
`include "mealy.v"

module mealy_tb();
wire OUT, STATE;
reg A, B;

mealy uut
(
    .OUT(OUT),
    .STATE(STATE),
    .A(A),
    .B(B)
);

initial
begin

    $dumpfile("dump.vcd");
    $dumpvars(0, mealy_tb);

    A = 0;                                      // add 0 and 0
    B = 0;
    #1;

    A = 1;                                      // add 1 and 0
    B = 0;
    #1;

    A = 0;                                      // add 0 and 1
    B = 1;
    #1;

    A = 1;                                      // test transition to carry state
    B = 1;
    #1;

    A = 1;                                      // test staying in carry state
    B = 0;
    #1;

    A = 1;
    B = 1;
    #1;

    A = 0;                                      // test exiting from the carry state
    B = 0;
    #1;

    A = 1;
    B = 0;
    #1;

    A = 0;
    B = 0;
    #1;

end
endmodule

cpe324/Homework1/Sim1/dump.vcd
$date
	Fri Feb 21 16:35:33 2020
$end
$version
	Icarus Verilog
$end
$timescale
	100ms
$end
$scope module mealy_tb $end
$var wire 1 ! STATE $end
$var wire 1 " OUT $end
$var reg 1 # A $end
$var reg 1 $ B $end
$scope module uut $end
$var wire 1 # A $end
$var wire 1 $ B $end
$var reg 1 % CARRY $end
$var reg 1 " OUT $end
$var reg 1 ! STATE $end
$upscope $end
$upscope $end
$enddefinitions $end
#0
$dumpvars
0%
0$
0#
0"
0!
$end
#10
1"
1#
#20
1$
0#
#30
1!
1%
0"
1#
#40
0$
#50
1"
1$
#60
0!
0%
0$
0#
#70
1#
#80
0"
0#
