cpe324/Homework1/Sim3/moore.v
module moore(A, B, OUT, STATE, clk); 
    input       A, B, clk;                                  // inputs to add             
    output reg  OUT;                                        // sum of the inputs
    parameter   CARRY = 0;                                  // carry bit
    output reg  [1:0] STATE = 0;                            // current state

    always @(posedge clk) 
    begin
        if(STATE == 0)                                      // in state 0
        begin
            if(A ^ B)                                       // if one of the inputs is one
            begin
                STATE = 1;                                  // transition to state 1
            end

            else if(A & B)                                  // if both inputs are 1
            begin
                STATE = 2;                                  // transition to state 2
            end
        end

        else if (STATE == 1)
        begin
            if(!A & !B)                                     // both inputs are 0
            begin
                STATE = 0;
            end

            else if(A & B)                                  // both inputs are 1
            begin
                STATE = 2;                                  // transition to state 2
            end
        end

        else if (STATE == 2)                                // if the current state is 2
        begin
            if(!A & !B)                                     // both inputs are 0
            begin
                STATE = 1;                                  // tranistion to state 1
            end

            else if(A & B)                                  // both inputs are 1
            begin
                STATE = 3;                                  // tranition to state 3
            end
        end

        else if (STATE == 3)                                // current state is 3
        begin
            if(!A & !B)                                     // if both inputs are 0
            begin
                STATE = 1;                                  // go to state 1
            end

            if(A ^ B)                                       // if one of the inputs is 1
            begin
                STATE = 2;                                  // go to state 2
            end
        end

        if(STATE == 0)
            OUT = 0;

        else if(STATE == 1)
            OUT = 1;

        else if(STATE == 2)
            OUT = 0;

        else if(STATE == 3)
            OUT = 1;
    end
endmodule

cpe324/Homework1/Sim3/moore_tb.v
`timescale 1ns/100 ps
`include "moore.v"

module moore_tb();
wire OUT;
wire [1:0] STATE;
reg A, B, clk = 0;

moore uut
(
    .OUT(OUT),
    .STATE(STATE),
    .A(A),
    .B(B),
    .clk(clk)
);

initial
begin

    $dumpfile("dump.vcd");
    $dumpvars(0, moore_tb);

    A = 0;
    B = 0;
    #10;
    
    A = 0;
    B = 1;
    #10;

    A = 1;
    B = 0;
    #10;

    A = 0;
    B = 0;
    #10;

    A = 1;
    B = 1;
    #10;

    A = 0;
    B = 1;
    #10;

    A = 0;
    B = 0;
    #10;

    A = 1;
    B = 1;
    #10;

    A = 1;
    B = 1;
    #10;

    A = 1;
    B = 1;
    #10;

    A = 1;
    B = 0;
    #10;

    A = 1;
    B = 1;
    #10;

    A = 0;
    B = 0;
    #10;
end

always
    #5  clk = ! clk; 

initial 
    #150  $finish; 
endmodule

cpe324/Homework1/Sim3/dump.vcd
$date
	Sun Feb 23 12:59:48 2020
$end
$version
	Icarus Verilog
$end
$timescale
	100ps
$end
$scope module moore_tb $end
$var wire 2 ! STATE [1:0] $end
$var wire 1 " OUT $end
$var reg 1 # A $end
$var reg 1 $ B $end
$var reg 1 % clk $end
$scope module uut $end
$var wire 1 # A $end
$var wire 1 $ B $end
$var wire 1 % clk $end
$var reg 1 " OUT $end
$var reg 2 & STATE [1:0] $end
$upscope $end
$upscope $end
$enddefinitions $end
#0
$dumpvars
b0 &
0%
0$
0#
x"
b0 !
$end
#50
0"
1%
#100
0%
1$
#150
1"
b1 !
b1 &
1%
#200
0%
0$
1#
#250
1%
#300
0%
0#
#350
0"
b0 !
b0 &
1%
#400
0%
1$
1#
#450
b10 !
b10 &
1%
#500
0%
0#
#550
1%
#600
0%
0$
#650
1"
b1 !
b1 &
1%
#700
0%
1$
1#
#750
0"
b10 !
b10 &
1%
#800
0%
#850
1"
b11 !
b11 &
1%
#900
0%
#950
1%
#1000
0%
0$
#1050
0"
b10 !
b10 &
1%
#1100
0%
1$
#1150
1"
b11 !
b11 &
1%
#1200
0%
0$
0#
#1250
b1 !
b1 &
1%
#1300
0%
#1350
0"
b0 !
b0 &
1%
